navneetop/__init__.py
navneetop-0.1.dist-info/LICENCE.txt
navneetop-0.1.dist-info/METADATA
navneetop-0.1.dist-info/WHEEL
navneetop-0.1.dist-info/top_level.txt
navneetop-0.1.dist-info/RECORD
