Metadata-Version: 2.1
Name: navneetop
Version: 0.1
Summary: Hii i am navneet and i am future developer.
Home-page: UNKNOWN
Author: Navneet Barmase
Author-email: maheshb7388@gmail.com
License: UNKNOWN
Platform: UNKNOWN
Classifier: Programming Language :: Python :: 3
Classifier: License :: OSI Approved :: MIT License
Classifier: Operating System :: OS Independent
License-File: LICENCE.txt
